carladam/__init__.py
carladam/diagram/__init__.py
carladam/diagram/digraph.py
carladam/diagram/geometry.py
carladam/diagram/kroki.py
carladam/diagram/lab.py
carladam/diagram/sequence.py
carladam/django/__init__.py
carladam/django/petrinet_simulator/__init__.py
carladam/django/petrinet_simulator/admin.py
carladam/django/petrinet_simulator/apps.py
carladam/django/petrinet_simulator/marking.py
carladam/django/petrinet_simulator/migrations/__init__.py
carladam/django/petrinet_simulator/models.py
carladam/django/petrinet_simulator/templates/petrinet_simulator/index.html
carladam/django/petrinet_simulator/templates/petrinet_simulator/simulator.html
carladam/django/petrinet_simulator/templatetags/__init__.py
carladam/django/petrinet_simulator/templatetags/petrinet_simulator.py
carladam/django/petrinet_simulator/tests.py
carladam/django/petrinet_simulator/urls.py
carladam/django/petrinet_simulator/views.py
carladam/django/simulator.py
carladam/petrinet/__init__.py
carladam/petrinet/arc.py
carladam/petrinet/color.py
carladam/petrinet/defaults.py
carladam/petrinet/effects.py
carladam/petrinet/errors.py
carladam/petrinet/marking.py
carladam/petrinet/occurrence.py
carladam/petrinet/petrinet.py
carladam/petrinet/place.py
carladam/petrinet/token.py
carladam/petrinet/transition.py
carladam/petrinet/types.py
carladam/util/__init__.py
carladam/util/autoname.py
carladam-0.1.0.dist-info/COPYING
carladam-0.1.0.dist-info/METADATA
carladam-0.1.0.dist-info/WHEEL
carladam-0.1.0.dist-info/RECORD
